elaina/__init__.py
elaina-0.10.17.dist-info/METADATA
elaina-0.10.17.dist-info/WHEEL
elaina-0.10.17.dist-info/top_level.txt
elaina-0.10.17.dist-info/RECORD
