Metadata-Version: 2.1
Name: elaina
Version: 0.10.17
Summary: elaina
Home-page: https://github.com/userElaina
Author: userElaina
Author-email: userElaina@google.com
License: UNKNOWN
Keywords: elaina
Platform: UNKNOWN
Classifier: Programming Language :: Python :: 3
Requires-Python: >=3.6
